clojurebridge/__init__.py
clojurebridge/cljbridge.py
cljbridge-0.0.8.dist-info/LICENSE
cljbridge-0.0.8.dist-info/METADATA
cljbridge-0.0.8.dist-info/WHEEL
cljbridge-0.0.8.dist-info/top_level.txt
cljbridge-0.0.8.dist-info/RECORD
