Metadata-Version: 2.1
Name: cljbridge
Version: 0.0.8
Summary: An extension og python-javabridge to start Clojure
Home-page: https://github.com/behrica/clojurebridge
Author: Carsten Behring
Author-email: carsten.behring@gmail.com
Project-URL: Bug Tracker, https://github.com/behrica/clojurebridge/issues
Classifier: Programming Language :: Python :: 3
Classifier: License :: OSI Approved :: MIT License
Classifier: Operating System :: OS Independent
Requires-Python: >=3.6
License-File: LICENSE
Requires-Dist: python-javabridge
